boruta_py_versioned/__init__.py
boruta_py_versioned/boruta_py.py
boruta_py_versioned/examples/Madalon_Data_Set.ipynb
boruta_py_versioned/examples/test_X.csv
boruta_py_versioned/examples/test_y.csv
boruta_py_versioned/test/__init__.py
boruta_py_versioned/test/unit_tests.py
boruta_py_versioned-0.1.0.dist-info/LICENSE
boruta_py_versioned-0.1.0.dist-info/METADATA
boruta_py_versioned-0.1.0.dist-info/WHEEL
boruta_py_versioned-0.1.0.dist-info/RECORD
