Metadata-Version: 2.1
Name: boruta_py_versioned
Version: 0.1.0
Summary: Fork of boruta_py with version added for poetry compatibility
Author: matteobolner
Author-email: matteo.bolner2@unibo.it
Requires-Python: >=3.10,<4
Classifier: Programming Language :: Python :: 3
Classifier: Programming Language :: Python :: 3.10
Classifier: Programming Language :: Python :: 3.11
Classifier: Programming Language :: Python :: 3.12
Requires-Dist: numpy (>=1.10.4)
Requires-Dist: scikit-learn (>=0.17.1)
Requires-Dist: scipy (>=0.17.0)
